ckanutils.py
ckanutils-0.14.9.dist-info/DESCRIPTION.rst
ckanutils-0.14.9.dist-info/METADATA
ckanutils-0.14.9.dist-info/pydist.json
ckanutils-0.14.9.dist-info/RECORD
ckanutils-0.14.9.dist-info/top_level.txt
ckanutils-0.14.9.dist-info/WHEEL
