Metadata-Version: 2.0
Name: ckanutils
Version: 0.14.9
Summary: Miscellaneous CKAN utility library
Home-page: https://github.com/reubano/ckanutils
Author: Reuben Cummings
Author-email: reubano@gmail.com
License: MIT
Keywords: c,k,a,n,u,t,i,l,s
Platform: MacOS X
Platform: Windows
Platform: Linux
Classifier: Development Status :: 4 - Beta
Classifier: License :: OSI Approved :: MIT License
Classifier: Natural Language :: English
Classifier: Programming Language :: Python :: 2
Classifier: Programming Language :: Python :: 2.7
Classifier: Environment :: Console
Classifier: Intended Audience :: Developers
Classifier: Intended Audience :: End Users/Desktop
Classifier: Operating System :: MacOS :: MacOS X
Classifier: Operating System :: POSIX
Classifier: Operating System :: POSIX :: Linux
Requires-Dist: ckanapi (==3.5)
Requires-Dist: chardet (==2.3.0)
Requires-Dist: manage.py (==0.2.10)
Requires-Dist: python-slugify (==0.0.7)
Requires-Dist: python-dateutil (==2.4.2)
Requires-Dist: requests (==2.8.1)
Requires-Dist: unicodecsv (==0.9.4)
Requires-Dist: xlrd (==0.9.3)
Requires-Dist: xattr (==0.7.5)
Requires-Dist: tabutils (==0.23.1)
